04_tabla_SOP/tabla04sop_tb.v
module tabla04sop();

// SOP de la tabla 04

  reg A, B, C, D;
  wire a1, a2, a3, a4, a5, a6, a7, Y;

  // not (salida, entrada);
  // or (salida, entrada1, entrada2, entrada3, etc);
  // and (salida, entrada1, entrada2, entrada3, etc);

  and  U1(a1, ~A, ~B, ~C, ~D);
  and  U2(a2, ~A, ~B,  C, ~D);
  and  U3(a3, ~A, ~B,  C,  D);
  and  U4(a4, ~A,  B,  C, ~D);
  and  U5(a5, ~A,  B,  C,  D);
  and  U5(a6,  A, ~B, ~C, ~D);
  and  U7(a7,  A, ~B,  C, ~D);

  or U8(Y, a1, a2, a3, a4, a5, a6, a7);


  initial begin
    $display("A B C D | Y");
    $display("--------|--");
    $monitor("%b %b %b %b | %b", A, B, C, D, Y);
       A = 0; B = 0; C = 0; D = 0;
    #1                      D = 1;
    #1               C = 1; D = 0;
    #1                      D = 1;
    #1        B = 1; C = 0; D = 0;
    #1                      D = 1;
    #1               C = 1; D = 0;
    #1                      D = 1;
    #1 A = 1; B = 0; C = 0; D = 0;
    #1                      D = 1;
    #1               C = 1; D = 0;
    #1                      D = 1;
    #1        B = 1; C = 0; D = 0;
    #1                      D = 1;
    #1               C = 1; D = 0;
    #1                      D = 1;
    #1 $finish;
  end

  initial
    begin
      $dumpfile("tabla04sop_tb.vcd");
      $dumpvars(0, tabla04sop);
    end

endmodule

04_tabla_SOP/tabla04sop_tb.vcd
$date
	Sat Aug  1 19:13:15 2020
$end
$version
	Icarus Verilog
$end
$timescale
	1ps
$end
$scope module tabla04sop $end
$var wire 1 ! Y $end
$var wire 1 " a1 $end
$var wire 1 # a2 $end
$var wire 1 $ a3 $end
$var wire 1 % a4 $end
$var wire 1 & a5 $end
$var wire 1 ' a6 $end
$var wire 1 ( a7 $end
$var reg 1 ) A $end
$var reg 1 * B $end
$var reg 1 + C $end
$var reg 1 , D $end
$upscope $end
$enddefinitions $end
#0
$dumpvars
0,
0+
0*
0)
0(
0'
0&
0%
0$
0#
1"
1!
$end
#1
0!
0"
1,
#2
1!
1#
0,
1+
#3
0#
1$
1,
#4
0!
0$
0,
0+
1*
#5
1,
#6
1!
1%
0,
1+
#7
0%
1&
1,
#8
1!
1'
0&
0,
0+
0*
1)
#9
0!
0'
1,
#10
1!
1(
0,
1+
#11
0!
0(
1,
#12
0,
0+
1*
#13
1,
#14
0,
1+
#15
1,
