ed1_lab4/ejercicio05/alarma.v
///// ELECTRÓNICA DIGITAL 1
///// AXEL MAZARIEGOS - 131212
///// 09 - AGOSTO - 2020
/////
///// LABORATORIO 04
///// EJERCIO 05




// SOP con Gate Level Modelling
// Ecuación a implementar: Y = (A * B' * C') + (A * B' * C) + (A * B * C);
module SOP_gateLevel(input wire A, B, C, output wire Y);

  wire notB, notC, a1, a2, a3;

  not (notB, B);
  not (notC, C);

  and (a1,    A, notB, notC);
  and (a2,    A, notB,    C);
  and (a3,    A,    B,    C);

  or  (Y, a1, a2, a3);

endmodule


// SOP con operadores
// Función a implementar: Y = (A * B' * C') + (A * B' * C) + (A * B * C);
module SOP_operadores(input wire A, B, C, output wire Y);

  assign Y = (A & ~B & ~C) | (A & ~B & C) | (A & B & C);

endmodule



// POS con Gate Level Modelling
// Ecuación a implementar:
// Y = (A + B + C) * (A + B + C') * (A + B' + C) * (A + B' + C') * (A' + B' + C) ;
module POS_gateLevel(input wire A, B, C, output wire Y);

  wire notA, notB, notC, o1, o2, o3, o4, o5;

  not (notA, A);
  not (notB, B);
  not (notC, C);

  or (o1,    A,    B,    C);
  or (o2,    A,    B, notC);
  or (o3,    A, notB,    C);
  or (o4,    A, notB, notC);
  or (o5, notA, notB,    C);

  and  (Y, o1, o2, o3, o4, o5);

endmodule


// POS con operadores
// Función a implementar:
// Y = (A + B + C) * (A + B + C') * (A + B' + C) * (A + B' + C') * (A' + B' + C) ;
module POS_operadores(input wire A, B, C, output wire Y);

  assign Y = (A | B | C) & (A | B | ~C) & (A | ~B | C) & (A | ~B | ~C) & (~A | ~B | C);

endmodule



// Ecuación simplificada con Gate Level Modelling
// Ecuación a implementar: Y = (A * B') + (A * C);
module ES_gateLevel(input wire A, B, C, output wire Y);

  wire notB, a1, a2;

  not (notB, B);


  and (a1,    A, notB);
  and (a2,    A,    C);

  or  (Y, a1, a2);

endmodule


// Ecuación simplificada con operadores
// Función a implementar: Y = (A * B') + (A * C);
module ES_operadores(input wire A, B, C, output wire Y);

  assign Y = (A & ~B) | (A & C);

endmodule

ed1_lab4/ejercicio05/alarma_tb.v
///// ELECTRÓNICA DIGITAL 1
///// AXEL MAZARIEGOS - 131212
///// 09 - AGOSTO - 2020
/////
///// LABORATORIO 04
///// EJERCIO 05



module alarma();

  reg p1, p2, p3;
  wire led1, led2, led3, led4, led5, led6;

  SOP_gateLevel SOPg(p1, p2, p3, led1);
  SOP_operadores SOPo(p1, p2, p3, led2);

  initial begin
    # 5 $display(" ");
    $display(" ");
    $display("     SOP     ");
    $display("A B C | Y1 Y2");
    $display("------|------");
    $monitor("%b %b %b | %b  %b", p1, p2, p3, led1, led2);
       p1 = 0; p2 = 0; p3 = 0;
    #1 p1 = 0; p2 = 0; p3 = 1;
    #1 p1 = 0; p2 = 1; p3 = 0;
    #1 p1 = 0; p2 = 1; p3 = 1;
    #1 p1 = 1; p2 = 0; p3 = 0;
    #1 p1 = 1; p2 = 0; p3 = 1;
    #1 p1 = 1; p2 = 1; p3 = 0;
    #1 p1 = 1; p2 = 1; p3 = 1;
  end


  POS_gateLevel POSg(p1, p2, p3, led3);
  POS_operadores POSo(p1, p2, p3, led4);

  initial begin
    #15 $display(" ");
    $display(" ");
    $display("     POS     ");
    $display("A B C | Y3 Y4");
    $display("------|------");
    $monitor("%b %b %b | %b  %b", p1, p2, p3, led3, led4);
       p1 = 0; p2 = 0; p3 = 0;
    #1 p1 = 0; p2 = 0; p3 = 1;
    #1 p1 = 0; p2 = 1; p3 = 0;
    #1 p1 = 0; p2 = 1; p3 = 1;
    #1 p1 = 1; p2 = 0; p3 = 0;
    #1 p1 = 1; p2 = 0; p3 = 1;
    #1 p1 = 1; p2 = 1; p3 = 0;
    #1 p1 = 1; p2 = 1; p3 = 1;
  end


  ES_gateLevel ESg(p1, p2, p3, led5);
  ES_operadores ESo(p1, p2, p3, led6);

  initial begin
    #25 $display(" ");
    $display(" ");
    $display("e. simplificada");
    $display("A B C | Y5 Y6");
    $display("------|------");
    $monitor("%b %b %b | %b  %b", p1, p2, p3, led5, led6);
       p1 = 0; p2 = 0; p3 = 0;
    #1 p1 = 0; p2 = 0; p3 = 1;
    #1 p1 = 0; p2 = 1; p3 = 0;
    #1 p1 = 0; p2 = 1; p3 = 1;
    #1 p1 = 1; p2 = 0; p3 = 0;
    #1 p1 = 1; p2 = 0; p3 = 1;
    #1 p1 = 1; p2 = 1; p3 = 0;
    #1 p1 = 1; p2 = 1; p3 = 1;
    #1 $display(" ");
    #1 $display(" ");
  end

  initial
    #35 $finish;


  initial begin
    $dumpfile("alarma_tb.vcd");
    $dumpvars(0, alarma);
  end

endmodule

ed1_lab4/ejercicio05/alarma_tb.vcd
$date
	Sun Aug  9 13:01:58 2020
$end
$version
	Icarus Verilog
$end
$timescale
	1ps
$end
$scope module alarma $end
$var wire 1 ! led6 $end
$var wire 1 " led5 $end
$var wire 1 # led4 $end
$var wire 1 $ led3 $end
$var wire 1 % led2 $end
$var wire 1 & led1 $end
$var reg 1 ' p1 $end
$var reg 1 ( p2 $end
$var reg 1 ) p3 $end
$scope module ESg $end
$var wire 1 ' A $end
$var wire 1 ( B $end
$var wire 1 ) C $end
$var wire 1 " Y $end
$var wire 1 * a1 $end
$var wire 1 + a2 $end
$var wire 1 , notB $end
$upscope $end
$scope module ESo $end
$var wire 1 ' A $end
$var wire 1 ( B $end
$var wire 1 ) C $end
$var wire 1 ! Y $end
$upscope $end
$scope module POSg $end
$var wire 1 ' A $end
$var wire 1 ( B $end
$var wire 1 ) C $end
$var wire 1 $ Y $end
$var wire 1 - notA $end
$var wire 1 . notB $end
$var wire 1 / notC $end
$var wire 1 0 o1 $end
$var wire 1 1 o2 $end
$var wire 1 2 o3 $end
$var wire 1 3 o4 $end
$var wire 1 4 o5 $end
$upscope $end
$scope module POSo $end
$var wire 1 ' A $end
$var wire 1 ( B $end
$var wire 1 ) C $end
$var wire 1 # Y $end
$upscope $end
$scope module SOPg $end
$var wire 1 ' A $end
$var wire 1 ( B $end
$var wire 1 ) C $end
$var wire 1 & Y $end
$var wire 1 5 a1 $end
$var wire 1 6 a2 $end
$var wire 1 7 a3 $end
$var wire 1 8 notB $end
$var wire 1 9 notC $end
$upscope $end
$scope module SOPo $end
$var wire 1 ' A $end
$var wire 1 ( B $end
$var wire 1 ) C $end
$var wire 1 % Y $end
$upscope $end
$upscope $end
$enddefinitions $end
#0
$dumpvars
x9
x8
x7
x6
x5
x4
x3
x2
x1
x0
x/
x.
x-
x,
x+
x*
x)
x(
x'
x&
x%
x$
x#
x"
x!
$end
#5
0#
0%
0$
11
12
13
0"
0!
0&
1/
14
19
1,
1.
18
0*
0+
1-
00
05
06
07
0)
0(
0'
#6
0$
01
0/
10
09
1)
#7
1/
02
19
0,
0.
11
08
0)
1(
#8
0$
03
0/
12
09
1)
#9
1%
1#
1"
1!
1&
1$
1*
15
1/
19
1,
1.
18
0-
13
0)
0(
1'
#10
05
1+
0/
09
16
1)
#11
0#
0$
0%
0"
0!
0&
0*
0+
1/
04
19
06
0,
0.
08
0)
1(
#12
1$
1"
1!
1#
1&
1%
1+
0/
14
09
17
1)
#15
0$
0#
0%
0"
0!
0&
1/
19
1,
1.
18
0+
1-
00
11
12
13
07
0)
0(
0'
#16
0$
01
0/
10
09
1)
#17
1/
02
19
0,
0.
11
08
0)
1(
#18
0$
03
0/
12
09
1)
#19
1%
1#
1"
1!
1&
1$
1*
15
1/
19
1,
1.
18
0-
13
0)
0(
1'
#20
05
1+
0/
09
16
1)
#21
0#
0$
0%
0"
0!
0&
0*
0+
1/
04
19
06
0,
0.
08
0)
1(
#22
1$
1"
1!
1#
1&
1%
1+
0/
14
09
17
1)
#25
0$
0#
0%
0"
0!
0&
1/
19
1,
1.
18
0+
1-
00
11
12
13
07
0)
0(
0'
#26
0$
01
0/
10
09
1)
#27
1/
02
19
0,
0.
11
08
0)
1(
#28
0$
03
0/
12
09
1)
#29
1%
1#
1"
1!
1&
1$
1*
15
1/
19
1,
1.
18
0-
13
0)
0(
1'
#30
05
1+
0/
09
16
1)
#31
0#
0$
0%
0"
0!
0&
0*
0+
1/
04
19
06
0,
0.
08
0)
1(
#32
1$
1"
1!
1#
1&
1%
1+
0/
14
09
17
1)
