ed1_lab9/ejercicio05/ejercicio5.v
///// ELECTRÓNICA DIGITAL 1
///// AXEL MAZARIEGOS - 131212
///// 31 - OCTUBRE - 2020
/////
///// LABORATORIO 09
///// EJERCICIO 05



module  ROM(input wire  [6:0] A,
            output reg  [12:0] Y);


  always @(A)
  begin

    if (A[0])

      casez (A) //casez para que reconozca los don't care
        7'b00001?1 : Y <= 13'b0100000001000;
        7'b00000?1 : Y <= 13'b1000000001000;
        7'b00011?1 : Y <= 13'b1000000001000;
        7'b00010?1 : Y <= 13'b0100000001000;
        7'b0010??1 : Y <= 13'b0001001000010;
        7'b0011??1 : Y <= 13'b1001001100000;
        7'b0100??1 : Y <= 13'b0011010000010;
        7'b0101??1 : Y <= 13'b0011010000100;
        7'b0110??1 : Y <= 13'b1011010100000;
        7'b0111??1 : Y <= 13'b1000000111000;
        7'b1000?11 : Y <= 13'b0100000001000;
        7'b1000?01 : Y <= 13'b1000000001000;
        7'b1001?11 : Y <= 13'b1000000001000;
        7'b1001?01 : Y <= 13'b0100000001000;
        7'b1010??1 : Y <= 13'b0011011000010;
        7'b1011??1 : Y <= 13'b1011011100000;
        7'b1100??1 : Y <= 13'b0100000001000;
        7'b1101??1 : Y <= 13'b0000000001001;
        7'b1110??1 : Y <= 13'b0011100000010;
        7'b1111??1 : Y <= 13'b1011100100000;
        default : Y =13'b0000000000000;

        endcase

      else Y <= 13'b1000000001000;

  end

endmodule





// este fue un modulo hecho escribiendo todoas las posibles combinaciones
// sin utilizar don't cares
/*module  ROM(input wire  [6:0] A,
            output reg  [12:0] Y);


  always @(A)
  begin

    if (A[0])

      case (A)
        7'b0000101 : Y <= 13'b0100000001000;
        7'b0000111 : Y <= 13'b0100000001000;

        7'b0000001 : Y <= 13'b1000000001000;
        7'b0000011 : Y <= 13'b1000000001000;

        7'b0001101 : Y <= 13'b1000000001000;
        7'b0001111 : Y <= 13'b1000000001000;

        7'b0001001 : Y <= 13'b0100000001000;
        7'b0001011 : Y <= 13'b0100000001000;

        7'b0010001 : Y <= 13'b0001001000010;
        7'b0010011 : Y <= 13'b0001001000010;
        7'b0010101 : Y <= 13'b0001001000010;
        7'b0010111 : Y <= 13'b0001001000010;

        7'b0011001 : Y <= 13'b1001001100000;
        7'b0011011 : Y <= 13'b1001001100000;
        7'b0011101 : Y <= 13'b1001001100000;
        7'b0011111 : Y <= 13'b1001001100000;

        7'b0100001 : Y <= 13'b0011010000010;
        7'b0100011 : Y <= 13'b0011010000010;
        7'b0100101 : Y <= 13'b0011010000010;
        7'b0100111 : Y <= 13'b0011010000010;

        7'b0101001 : Y <= 13'b0011010000100;
        7'b0101011 : Y <= 13'b0011010000100;
        7'b0101101 : Y <= 13'b0011010000100;
        7'b0101111 : Y <= 13'b0011010000100;

        7'b0110001 : Y <= 13'b1011010100000;
        7'b0110011 : Y <= 13'b1011010100000;
        7'b0110101 : Y <= 13'b1011010100000;
        7'b0110111 : Y <= 13'b1011010100000;

        7'b0111001 : Y <= 13'b1000000111000;
        7'b0111011 : Y <= 13'b1000000111000;
        7'b0111101 : Y <= 13'b1000000111000;
        7'b0111111 : Y <= 13'b1000000111000;

        7'b1000011 : Y <= 13'b0100000001000;
        7'b1000111 : Y <= 13'b0100000001000;

        7'b1000001 : Y <= 13'b1000000001000;
        7'b1000101 : Y <= 13'b1000000001000;

        7'b1001011 : Y <= 13'b1000000001000;
        7'b1001111 : Y <= 13'b1000000001000;

        7'b1001001 : Y <= 13'b0100000001000;
        7'b1001101 : Y <= 13'b0100000001000;

        7'b1010001 : Y <= 13'b0011011000010;
        7'b1010011 : Y <= 13'b0011011000010;
        7'b1010101 : Y <= 13'b0011011000010;
        7'b1010111 : Y <= 13'b0011011000010;

        7'b1011001 : Y <= 13'b1011011100000;
        7'b1011011 : Y <= 13'b1011011100000;
        7'b1011101 : Y <= 13'b1011011100000;
        7'b1011111 : Y <= 13'b1011011100000;
        
        7'b1100001 : Y <= 13'b0100000001000;
        7'b1100011 : Y <= 13'b0100000001000;
        7'b1100101 : Y <= 13'b0100000001000;
        7'b1100111 : Y <= 13'b0100000001000;
        
        7'b1101001 : Y <= 13'b0000000001001;
        7'b1101011 : Y <= 13'b0000000001001;
        7'b1101101 : Y <= 13'b0000000001001;
        7'b1101111 : Y <= 13'b0000000001001;
        
        7'b1110001 : Y <= 13'b0011100000010;
        7'b1110011 : Y <= 13'b0011100000010;
        7'b1110101 : Y <= 13'b0011100000010;
        7'b1110111 : Y <= 13'b0011100000010;

        7'b1111001 : Y <= 13'b1011100100000;
        7'b1111011 : Y <= 13'b1011100100000;
        7'b1111101 : Y <= 13'b1011100100000;
        7'b1111111 : Y <= 13'b1011100100000;

        default : Y =13'b0000000000000;

        endcase

      //cuando el bit menos signifcativo es 0
      else Y <= 13'b1000000001000; 

  end

endmodule */

ed1_lab9/ejercicio05/ejercicio5_tb.v
///// ELECTRÓNICA DIGITAL 1
///// AXEL MAZARIEGOS - 131212
///// 31 - OCTUBRE - 2020
/////
///// LABORATORIO 09
///// EJERCICIO 05


module ejercicio5();


reg [6:0] entrada;
wire [12:0] salida;

ROM U1(entrada, salida);

initial begin
   #1 $display(" ");
   $display(" ");
   $display("ROM con cases");
   $display("A       |   Y");
   $display("--------|--------------");
   $monitor(" %b | %b  ", entrada, salida);
   end

initial begin

//pruebas con entrada[0] = 0
//any
    entrada =7'b1111110 ;
#10 entrada =7'b0101010 ;
#10 entrada =7'b1010100 ;
#10 entrada =7'b1100110 ;

//JC
#10 entrada =7'b0000101 ;
#10 entrada =7'b0000111 ;

//JC
#10 entrada =7'b0000001 ;
#10 entrada =7'b0000011 ;

//JNC
#10 entrada =7'b0001101 ;
#10 entrada =7'b0001111 ;

//JNC
#10 entrada =7'b0001001 ;
#10 entrada =7'b0001011 ;

//CMPI
#10 entrada =7'b0010011 ;
#10 entrada =7'b0010101 ;

//CMPM
#10 entrada =7'b0011001 ;
#10 entrada =7'b0011111 ;

//LIT
#10 entrada =7'b0100011 ;
#10 entrada =7'b0100101 ;

//IN
#10 entrada =7'b0101001 ;
#10 entrada =7'b0101111 ;

//LD
#10 entrada =7'b0110011 ;
#10 entrada =7'b0110101 ;

//ST
#10 entrada =7'b0111001 ;
#10 entrada =7'b0111111 ;

//JZ
#10 entrada =7'b1000011 ;
#10 entrada =7'b1000111 ;

//JZ
#10 entrada =7'b1000001 ;
#10 entrada =7'b1000101 ;

//JNZ
#10 entrada =7'b1001011 ;
#10 entrada =7'b1001111 ;

//JNZ
#10 entrada =7'b1001001 ;
#10 entrada =7'b1001101 ;

//ADDI
#10 entrada =7'b1010001 ;
#10 entrada =7'b1010111 ;

//ADDM
#10 entrada =7'b1011011 ;
#10 entrada =7'b1011101 ;

//JMP
#10 entrada =7'b1100001 ;
#10 entrada =7'b1100111 ;

//OUT
#10 entrada =7'b1101011 ;
#10 entrada =7'b1101101 ;

//NORI
#10 entrada =7'b1110001 ;
#10 entrada =7'b1110111 ;

//NORM
#10 entrada =7'b1111011 ;
#10 entrada =7'b1111101 ;


 #10 $finish;
end




  initial begin
    $dumpfile("ejercicio5_tb.vcd");
    $dumpvars(0, ejercicio5);
  end

endmodule

ed1_lab9/ejercicio05/ejercicio5_tb.vcd
$date
	Sat Oct 31 11:06:52 2020
$end
$version
	Icarus Verilog
$end
$timescale
	1ps
$end
$scope module ejercicio5 $end
$var wire 13 ! salida [12:0] $end
$var reg 7 " entrada [6:0] $end
$scope module U1 $end
$var wire 7 # A [6:0] $end
$var reg 13 $ Y [12:0] $end
$upscope $end
$upscope $end
$enddefinitions $end
#0
$dumpvars
b1000000001000 $
b1111110 #
b1111110 "
b1000000001000 !
$end
#10
b101010 "
b101010 #
#20
b1010100 "
b1010100 #
#30
b1100110 "
b1100110 #
#40
b100000001000 !
b100000001000 $
b101 "
b101 #
#50
b111 "
b111 #
#60
b1000000001000 !
b1000000001000 $
b1 "
b1 #
#70
b11 "
b11 #
#80
b1101 "
b1101 #
#90
b1111 "
b1111 #
#100
b100000001000 !
b100000001000 $
b1001 "
b1001 #
#110
b1011 "
b1011 #
#120
b1001000010 !
b1001000010 $
b10011 "
b10011 #
#130
b10101 "
b10101 #
#140
b1001001100000 !
b1001001100000 $
b11001 "
b11001 #
#150
b11111 "
b11111 #
#160
b11010000010 !
b11010000010 $
b100011 "
b100011 #
#170
b100101 "
b100101 #
#180
b11010000100 !
b11010000100 $
b101001 "
b101001 #
#190
b101111 "
b101111 #
#200
b1011010100000 !
b1011010100000 $
b110011 "
b110011 #
#210
b110101 "
b110101 #
#220
b1000000111000 !
b1000000111000 $
b111001 "
b111001 #
#230
b111111 "
b111111 #
#240
b100000001000 !
b100000001000 $
b1000011 "
b1000011 #
#250
b1000111 "
b1000111 #
#260
b1000000001000 !
b1000000001000 $
b1000001 "
b1000001 #
#270
b1000101 "
b1000101 #
#280
b1001011 "
b1001011 #
#290
b1001111 "
b1001111 #
#300
b100000001000 !
b100000001000 $
b1001001 "
b1001001 #
#310
b1001101 "
b1001101 #
#320
b11011000010 !
b11011000010 $
b1010001 "
b1010001 #
#330
b1010111 "
b1010111 #
#340
b1011011100000 !
b1011011100000 $
b1011011 "
b1011011 #
#350
b1011101 "
b1011101 #
#360
b100000001000 !
b100000001000 $
b1100001 "
b1100001 #
#370
b1100111 "
b1100111 #
#380
b1001 !
b1001 $
b1101011 "
b1101011 #
#390
b1101101 "
b1101101 #
#400
b11100000010 !
b11100000010 $
b1110001 "
b1110001 #
#410
b1110111 "
b1110111 #
#420
b1011100100000 !
b1011100100000 $
b1111011 "
b1111011 #
#430
b1111101 "
b1111101 #
