ed1_lab9/ejercicio03/ejercicio3.v
///// ELECTRÓNICA DIGITAL 1
///// AXEL MAZARIEGOS - 131212
///// 30 - OCTUBRE - 2020
/////
///// LABORATORIO 09
///// EJERCICIO 03


// Flip Flop tipo D
module FFD(input wire clk, reset, enable, D, output reg Q);

  always @(posedge clk or posedge reset or posedge enable)
    begin
      if (reset) Q <= 1'b0;
      else if (enable) Q <= D;
      else Q <= Q;
    end

endmodule


// Flip Flop tipo J K
module FFJK(input wire clk, reset, enable, J, K, output wire Q);

  wire nQ, nK, a1, a2, D;

  // not (salida, entrada);
  // or (salida, entrada1, entrada2, entrada3, etc);
  // and (salida, entrada1, entrada2, entrada3, etc);
  not U1(nQ, Q);
  not U2(nK, K);

  and U3(a1, nQ, J);
  and U4(a2, Q, nK);
  
  or  U5(D, a1, a2);

  FFD U6(clk, reset, enable, D, Q);
  
  
endmodule

ed1_lab9/ejercicio03/ejercicio3_tb.v
///// ELECTRÓNICA DIGITAL 1
///// AXEL MAZARIEGOS - 131212
///// 30 - OCTUBRE - 2020
/////
///// LABORATORIO 09
///// EJERCICIO 03


module ejercicio3();

  //para las pruebas se usara el mismo clock, reset y enable para todos los FF
  reg clk, reset, enable;
  reg j, k;
  wire q;


  FFJK U1(clk, reset, enable, j, k, q);

  initial begin
    #5 $display(" ");
    $display(" ");
    $display(" FFJK ");
    $display("c r e j k | q");
    $display("----------|---");
    $monitor("%b %b %b %b %b | %b ", clk, reset, enable, j, k, q);
  end

  initial begin
  
    j = 0;
    k = 0;
    

    clk = 0;
    reset = 1;
    enable = 0;
    #3

//
    j = 1;
    k = 0;

    reset = 0;
    enable = 1;
    #10

    //enable = 0;
    #10

//

    j = 0;
    k = 0;

    enable = 1;
    #10

    //enable = 0;
    #10


//

    j = 0;
    k = 1;

    enable = 1;
    #10

    //enable = 0;
    #10

//


//

    j = 1;
    k = 1;

    enable = 1;
    #30

    enable = 0;
    #10

//





    reset = 1;
    #6



    $finish;
  end

  always
    #2 clk = ~clk;


  initial begin
    $dumpfile("ejercicio3_tb.vcd");
    $dumpvars(0, ejercicio3);
  end

endmodule

ed1_lab9/ejercicio03/ejercicio3_tb.vcd
$date
	Fri Oct 30 20:40:32 2020
$end
$version
	Icarus Verilog
$end
$timescale
	1ps
$end
$scope module ejercicio3 $end
$var wire 1 ! q $end
$var reg 1 " clk $end
$var reg 1 # enable $end
$var reg 1 $ j $end
$var reg 1 % k $end
$var reg 1 & reset $end
$scope module U1 $end
$var wire 1 ' D $end
$var wire 1 $ J $end
$var wire 1 % K $end
$var wire 1 ( a1 $end
$var wire 1 ) a2 $end
$var wire 1 " clk $end
$var wire 1 # enable $end
$var wire 1 * nK $end
$var wire 1 + nQ $end
$var wire 1 & reset $end
$var wire 1 ! Q $end
$scope module U6 $end
$var wire 1 ' D $end
$var wire 1 " clk $end
$var wire 1 # enable $end
$var wire 1 & reset $end
$var reg 1 ! Q $end
$upscope $end
$upscope $end
$upscope $end
$enddefinitions $end
#0
$dumpvars
1+
1*
0)
0(
0'
1&
0%
0$
0#
0"
0!
$end
#2
1"
#3
1'
1(
1#
0&
1$
#4
0"
#6
0(
1)
0+
1!
1"
#8
0"
#10
1"
#12
0"
#14
1"
#16
0"
#18
1"
#20
0"
#22
1"
#23
0$
#24
0"
#26
1"
#28
0"
#30
1"
#32
0"
#34
1"
#36
0"
#38
1"
#40
0"
#42
1"
#43
0'
0)
0*
1%
#44
0"
#46
1+
0!
1"
#48
0"
#50
1"
#52
0"
#54
1"
#56
0"
#58
1"
#60
0"
#62
1"
#63
1'
1(
1$
#64
0"
#66
0'
0(
0+
1!
1"
#68
0"
#70
1'
1(
1+
0!
1"
#72
0"
#74
0'
0(
0+
1!
1"
#76
0"
#78
1'
1(
1+
0!
1"
#80
0"
#82
0'
0(
0+
1!
1"
#84
0"
#86
1'
1(
1+
0!
1"
#88
0"
#90
0'
0(
0+
1!
1"
#92
0"
#93
0#
#94
1"
#96
0"
#98
1"
#100
0"
#102
1"
#103
1'
1(
1+
0!
1&
