ed1_lab3/01_tabla_POS/tabla01pos_tb.v
module tabla01pos();

// POS de la tabla 01

  reg A, B, C;
  wire nA, nB, nC, o1, o2, o3, Y;

  // not (salida, entrada);
  // or (salida, entrada1, entrada2, entrada3, etc);
  // and (salida, entrada1, entrada2, entrada3, etc);
  not U1(nA, A);
  not U2(nB, B);
  not U3(nC, C);

  or  U4(o1,  A,  B, nC);
  or  U5(o2,  A, nB, nC);
  or  U6(o3, nA, nB,  C);

  and U7(Y, o1, o2, o3);


  initial begin
    $display("A B C | Y");
    $display("------|--");
    $monitor("%b %b %b | %b", A, B, C, Y);
    A = 0; B = 0; C = 0;
    #1 A = 0; B = 0; C = 1;
    #1 A = 0; B = 1; C = 0;
    #1 A = 0; B = 1; C = 1;
    #1 A = 1; B = 0; C = 0;
    #1 A = 1; B = 0; C = 1;
    #1 A = 1; B = 1; C = 0;
    #1 A = 1; B = 1; C = 1;
    #1 $finish;
  end

  initial
    begin
      $dumpfile("tabla01pos_tb.vcd");
      $dumpvars(0, tabla01pos);
    end

endmodule

01_tabla_POS/tabla01pos_tb.vcd
$date
	Sat Aug  1 18:05:57 2020
$end
$version
	Icarus Verilog
$end
$timescale
	1ps
$end
$scope module tabla01pos $end
$var wire 1 ! Y $end
$var wire 1 " nA $end
$var wire 1 # nB $end
$var wire 1 $ nC $end
$var wire 1 % o1 $end
$var wire 1 & o2 $end
$var wire 1 ' o3 $end
$var reg 1 ( A $end
$var reg 1 ) B $end
$var reg 1 * C $end
$upscope $end
$enddefinitions $end
#0
$dumpvars
0*
0)
0(
1'
1&
1%
1$
1#
1"
1!
$end
#1
0!
0%
0$
1*
#2
1!
1$
1%
0#
0*
1)
#3
0!
0&
0$
1*
#4
1!
1$
1#
1&
0"
0*
0)
1(
#5
0$
1*
#6
0!
0'
1$
0#
0*
1)
#7
1!
1'
0$
1*
