ed1_lab9/ejercicio02/ejercicio2.v
///// ELECTRÓNICA DIGITAL 1
///// AXEL MAZARIEGOS - 131212
///// 30 - OCTUBRE - 2020
/////
///// LABORATORIO 09
///// EJERCICIO 02


// Flip Flop tipo D
module FFD(input wire clk, reset, enable, D, output reg Q);

  always @(posedge clk or posedge reset or posedge enable)
    begin
      if (reset) Q <= 1'b0;
      else if (enable) Q <= D;
      else Q <= Q;
    end

endmodule


// Flip Flop tipo T
module FFT(input wire clk, reset, enable, output wire T);

  wire cable;
  not U1(cable, T);
  
  FFD U2(clk, reset, enable, cable, T);


endmodule


/* //Este flip flip devulve el negado de la entrada
//no es necesario para el laboratorio 
module FFX(input wire clk, reset, enable, D, Q, output reg N);

  FFD U1(clk, reset, enable, D, Q);


  always @(posedge clk or posedge reset or enable)
    begin
      if (reset)  N <= 1'b0;
      else if (enable) N <= ~D;
      else  N <= ~Q;
    end

endmodule
*/

ed1_lab9/ejercicio02/ejercicio2_tb.v
///// ELECTRÓNICA DIGITAL 1
///// AXEL MAZARIEGOS - 131212
///// 30 - OCTUBRE - 2020
/////
///// LABORATORIO 09
///// EJERCICIO 02


module ejercicio2();

  //para las pruebas se usara el mismo clock, reset y enable para todos los FF
  reg clk, reset, enable;

  wire q;
 
  
  FFT U2(clk, reset, enable, q);
  

  initial begin
    #5 $display(" ");
    $display(" ");
    $display(" FFD y FFT ");
    $display("c r e | q");
    $display("------|----");
    $monitor("%b %b %b | %b ", clk, reset, enable, q,);
  end

  initial begin
   
    clk = 0;
    reset = 1;
    enable = 0;
    #10

    reset = 0;
    enable = 1;
    #30

    enable = 0;
    #10

   
    enable = 1;
    #25

    enable = 0;
    #10

    reset = 1;
    #6



    $finish;
  end

  always
    #2 clk = ~clk;


  initial begin
    $dumpfile("ejercicio2_tb.vcd");
    $dumpvars(0, ejercicio2);
  end

endmodule

ed1_lab9/ejercicio02/ejercicio2_tb.vcd
$date
	Fri Oct 30 18:27:41 2020
$end
$version
	Icarus Verilog
$end
$timescale
	1ps
$end
$scope module ejercicio2 $end
$var wire 1 ! q $end
$var reg 1 " clk $end
$var reg 1 # enable $end
$var reg 1 $ reset $end
$scope module U2 $end
$var wire 1 % cable $end
$var wire 1 " clk $end
$var wire 1 # enable $end
$var wire 1 $ reset $end
$var wire 1 ! T $end
$scope module U2 $end
$var wire 1 % D $end
$var wire 1 " clk $end
$var wire 1 # enable $end
$var wire 1 $ reset $end
$var reg 1 ! Q $end
$upscope $end
$upscope $end
$upscope $end
$enddefinitions $end
#0
$dumpvars
1%
1$
0#
0"
0!
$end
#2
1"
#4
0"
#6
1"
#8
0"
#10
0%
1!
1"
1#
0$
#12
0"
#14
1%
0!
1"
#16
0"
#18
0%
1!
1"
#20
0"
#22
1%
0!
1"
#24
0"
#26
0%
1!
1"
#28
0"
#30
1%
0!
1"
#32
0"
#34
0%
1!
1"
#36
0"
#38
1%
0!
1"
#40
0"
0#
#42
1"
#44
0"
#46
1"
#48
0"
#50
0%
1!
1"
1#
#52
0"
#54
1%
0!
1"
#56
0"
#58
0%
1!
1"
#60
0"
#62
1%
0!
1"
#64
0"
#66
0%
1!
1"
#68
0"
#70
1%
0!
1"
#72
0"
#74
0%
1!
1"
#75
0#
#76
0"
#78
1"
#80
0"
#82
1"
#84
0"
#85
1%
0!
1$
