ed1_lab4/ed1_lab4.v
///// ELECTRÓNICA DIGITAL 1
///// AXEL MAZARIEGOS - 131212
///// 09 - AGOSTO - 2020
/////
///// LABORATORIO 04
///// EJERCIO 04


// EJERCICIO 01_01
// Función a implementar: Y = (A' * C') + (A * C) + (B' * C')

module operadores1_1(input wire A, B, C, output wire Y);

  assign Y = (~A & ~C) | (A & C) | (~B & ~C);

endmodule


// EJERCICIO 01_02
// Ecuación a implementar: Y = B';

module gateLevel1_2(input wire B, output wire Y);

  not (Y, B);

endmodule


// EJERCICIO 01_03
// Ecuación a implementar:
// Y = (A' * B' * C' * D') + (A' * B' * C * D) + (A' * B * C' * D) + (A' * B * C * D')
//    + (A * B * C' * D') + (A * B * C * D) + (A * B' * C' * D) + (A * B' * C * D');

module gateLevel1_3(input wire A, B, C, D, output wire Y);

  wire notA, notB, notC, notD, a1, a2, a3, a4, a5 ,a6, a7, a8;

  not (notA, A);
  not (notB, B);
  not (notC, C);
  not (notD, D);

  and (a1, notA, notB, notC, notD);
  and (a2, notA, notB,    C,    D);
  and (a3, notA,    B, notC,    D);
  and (a4, notA,    B,    C, notD);
  and (a5,    A,    B, notC, notD);
  and (a6,    A,    B,    C,    D);
  and (a7,    A, notB, notC,    D);
  and (a8,    A, notB,    C, notD);

  or  (Y, a1, a2, a3, a4, a5 ,a6, a7, a8);

  endmodule


// EJERCICIO 01_04
// Función a implementar: Y = (B' * D') + (B * D) + (A * B) + (A * C);

module operadores1_4(input wire A, B, C, D, output wire Y);

  assign Y = (~B & ~D) | (B & D) | (A & B) | (A & C);

endmodule



// EJERCICIO 02_01
// Función a implementar: Y = (B' * C' * D') + (A * C') + (A * B') + (A * C * D');
module operadores2_1(input wire A, B, C, D, output wire Y);

  assign Y = (~B & ~C & ~D) | (A & ~C) | (A & ~B) | (A & C & ~D);

endmodule


// EJERCICIO 02_02
// Ecuación a implementar:
// Y = (B' * C') + (C)

module gateLevel2_2(input wire B, C, output wire Y);

  wire notB, notC, a1;

  not (notB, B);
  not (notC, C);

  and (a1, notB, notC);

  or  (Y, a1, C);

endmodule


// EJERCICIO 02_03
// Función a implementar: Y = (B) + (C' * D) + (A * D);
module operadores2_3(input wire A, B, C, D, output wire Y);

  assign Y = (B) | (~C & D) | (A & D);

endmodule


// EJERCICIO 02_04
// Ecuación a implementar:
// Y = (B) + (A' * C')
module gateLevel2_4(input wire A, B, C, output wire Y);

  wire notA, notC, a1;

  not (notA, A);
  not (notC, C);

  and (a1, notA, notC);

  or  (Y, a1, B);

endmodule

ed1_lab4/ejercicio04/ed1_lab4_tb.v
///// ELECTRÓNICA DIGITAL 1
///// AXEL MAZARIEGOS - 131212
///// 09 - AGOSTO - 2020
/////
///// LABORATORIO 04
///// EJERCIO 04



module testbench();

  reg p1, p2, p3, p4;
  wire led1, led2, led3, led4, led5, led6, led7, led8;

  operadores1_1 OP1(p1, p2, p3, led1);
  gateLevel1_2 GL1(p2, led2);

  initial begin
    # 5 $display(" ");
    $display(" ");
    $display(" Tabla 1 y 2");
    $display("A B C | Y1 Y2");
    $display("------|------");
    $monitor("%b %b %b | %b  %b", p1, p2, p3, led1, led2);
       p1 = 0; p2 = 0; p3 = 0;
    #1 p1 = 0; p2 = 0; p3 = 1;
    #1 p1 = 0; p2 = 1; p3 = 0;
    #1 p1 = 0; p2 = 1; p3 = 1;
    #1 p1 = 1; p2 = 0; p3 = 0;
    #1 p1 = 1; p2 = 0; p3 = 1;
    #1 p1 = 1; p2 = 1; p3 = 0;
    #1 p1 = 1; p2 = 1; p3 = 1;
  end


  gateLevel1_3 GL3(p1, p2, p3, p4, led3);
  operadores1_4 OP4(p1, p2, p3, p4, led4);

  initial begin
    #15 $display(" ");
    $display(" Tabla 3 y 4");
    $display("A B C D | Y3 Y4");
    $display("--------|------");
    $monitor("%b %b %b %b | %b  %b", p1, p2, p3, p4, led3, led4);
       p1 = 0; p2 = 0; p3 = 0; p4 = 0;
    #1 p1 = 0; p2 = 0; p3 = 0; p4 = 1;
    #1 p1 = 0; p2 = 0; p3 = 1; p4 = 0;
    #1 p1 = 0; p2 = 0; p3 = 1; p4 = 1;
    #1 p1 = 0; p2 = 1; p3 = 0; p4 = 0;
    #1 p1 = 0; p2 = 1; p3 = 0; p4 = 1;
    #1 p1 = 0; p2 = 1; p3 = 1; p4 = 0;
    #1 p1 = 0; p2 = 1; p3 = 1; p4 = 1;
    #1 p1 = 1; p2 = 0; p3 = 0; p4 = 0;
    #1 p1 = 1; p2 = 0; p3 = 0; p4 = 1;
    #1 p1 = 1; p2 = 0; p3 = 1; p4 = 0;
    #1 p1 = 1; p2 = 0; p3 = 1; p4 = 1;
    #1 p1 = 1; p2 = 1; p3 = 0; p4 = 0;
    #1 p1 = 1; p2 = 1; p3 = 0; p4 = 1;
    #1 p1 = 1; p2 = 1; p3 = 1; p4 = 0;
    #1 p1 = 1; p2 = 1; p3 = 1; p4 = 1;

  end


  operadores2_1 OP5(p1, p2, p3, p4, led5);
  gateLevel2_2 GL6(p2, p3, led6);

  initial begin
    #35 $display(" ");
    $display(" Tabla 5 y 6");
    $display("A B C D | Y5 Y6");
    $display("--------|------");
    $monitor("%b %b %b %b | %b  %b", p1, p2, p3, p4, led5, led6);
       p1 = 0; p2 = 0; p3 = 0; p4 = 0;
    #1 p1 = 0; p2 = 0; p3 = 0; p4 = 1;
    #1 p1 = 0; p2 = 0; p3 = 1; p4 = 0;
    #1 p1 = 0; p2 = 0; p3 = 1; p4 = 1;
    #1 p1 = 0; p2 = 1; p3 = 0; p4 = 0;
    #1 p1 = 0; p2 = 1; p3 = 0; p4 = 1;
    #1 p1 = 0; p2 = 1; p3 = 1; p4 = 0;
    #1 p1 = 0; p2 = 1; p3 = 1; p4 = 1;
    #1 p1 = 1; p2 = 0; p3 = 0; p4 = 0;
    #1 p1 = 1; p2 = 0; p3 = 0; p4 = 1;
    #1 p1 = 1; p2 = 0; p3 = 1; p4 = 0;
    #1 p1 = 1; p2 = 0; p3 = 1; p4 = 1;
    #1 p1 = 1; p2 = 1; p3 = 0; p4 = 0;
    #1 p1 = 1; p2 = 1; p3 = 0; p4 = 1;
    #1 p1 = 1; p2 = 1; p3 = 1; p4 = 0;
    #1 p1 = 1; p2 = 1; p3 = 1; p4 = 1;

  end



  operadores2_3 OP7(p1, p2, p3, p4, led7);
  gateLevel2_4 GL8(p1, p2, p3, led8);

  initial begin
    #55 $display(" ");
    $display(" Tabla 7 y 8");
    $display("A B C D | Y7 Y8");
    $display("--------|------");
    $monitor("%b %b %b %b | %b  %b", p1, p2, p3, p4, led7, led8);
       p1 = 0; p2 = 0; p3 = 0; p4 = 0;
    #1 p1 = 0; p2 = 0; p3 = 0; p4 = 1;
    #1 p1 = 0; p2 = 0; p3 = 1; p4 = 0;
    #1 p1 = 0; p2 = 0; p3 = 1; p4 = 1;
    #1 p1 = 0; p2 = 1; p3 = 0; p4 = 0;
    #1 p1 = 0; p2 = 1; p3 = 0; p4 = 1;
    #1 p1 = 0; p2 = 1; p3 = 1; p4 = 0;
    #1 p1 = 0; p2 = 1; p3 = 1; p4 = 1;
    #1 p1 = 1; p2 = 0; p3 = 0; p4 = 0;
    #1 p1 = 1; p2 = 0; p3 = 0; p4 = 1;
    #1 p1 = 1; p2 = 0; p3 = 1; p4 = 0;
    #1 p1 = 1; p2 = 0; p3 = 1; p4 = 1;
    #1 p1 = 1; p2 = 1; p3 = 0; p4 = 0;
    #1 p1 = 1; p2 = 1; p3 = 0; p4 = 1;
    #1 p1 = 1; p2 = 1; p3 = 1; p4 = 0;
    #1 p1 = 1; p2 = 1; p3 = 1; p4 = 1;
    #1 $display(" ");
    #1 $display(" ");

  end

  initial
    #75 $finish;


  initial begin
    $dumpfile("ed1_lab4_tb.vcd");
    $dumpvars(0, testbench);
  end

endmodule

ed1_lab4/ed1_lab4_tb.vcd
$date
	Sun Aug  9 11:06:29 2020
$end
$version
	Icarus Verilog
$end
$timescale
	1ps
$end
$scope module testbench $end
$var wire 1 ! led8 $end
$var wire 1 " led7 $end
$var wire 1 # led6 $end
$var wire 1 $ led5 $end
$var wire 1 % led4 $end
$var wire 1 & led3 $end
$var wire 1 ' led2 $end
$var wire 1 ( led1 $end
$var reg 1 ) p1 $end
$var reg 1 * p2 $end
$var reg 1 + p3 $end
$var reg 1 , p4 $end
$scope module GL1 $end
$var wire 1 * B $end
$var wire 1 ' Y $end
$upscope $end
$scope module GL3 $end
$var wire 1 ) A $end
$var wire 1 * B $end
$var wire 1 + C $end
$var wire 1 , D $end
$var wire 1 & Y $end
$var wire 1 - a1 $end
$var wire 1 . a2 $end
$var wire 1 / a3 $end
$var wire 1 0 a4 $end
$var wire 1 1 a5 $end
$var wire 1 2 a6 $end
$var wire 1 3 a7 $end
$var wire 1 4 a8 $end
$var wire 1 5 notA $end
$var wire 1 6 notB $end
$var wire 1 7 notC $end
$var wire 1 8 notD $end
$upscope $end
$scope module GL6 $end
$var wire 1 * B $end
$var wire 1 + C $end
$var wire 1 # Y $end
$var wire 1 9 a1 $end
$var wire 1 : notB $end
$var wire 1 ; notC $end
$upscope $end
$scope module GL8 $end
$var wire 1 ) A $end
$var wire 1 * B $end
$var wire 1 + C $end
$var wire 1 ! Y $end
$var wire 1 < a1 $end
$var wire 1 = notA $end
$var wire 1 > notC $end
$upscope $end
$scope module OP1 $end
$var wire 1 ) A $end
$var wire 1 * B $end
$var wire 1 + C $end
$var wire 1 ( Y $end
$upscope $end
$scope module OP4 $end
$var wire 1 ) A $end
$var wire 1 * B $end
$var wire 1 + C $end
$var wire 1 , D $end
$var wire 1 % Y $end
$upscope $end
$scope module OP5 $end
$var wire 1 ) A $end
$var wire 1 * B $end
$var wire 1 + C $end
$var wire 1 , D $end
$var wire 1 $ Y $end
$upscope $end
$scope module OP7 $end
$var wire 1 ) A $end
$var wire 1 * B $end
$var wire 1 + C $end
$var wire 1 , D $end
$var wire 1 " Y $end
$upscope $end
$upscope $end
$enddefinitions $end
#0
$dumpvars
x>
x=
x<
x;
x:
x9
x8
x7
x6
x5
x4
x3
x2
x1
x0
x/
x.
x-
x,
x+
x*
x)
x(
x'
x&
x%
x$
x#
x"
x!
$end
#5
1#
1(
1!
19
1<
17
0.
1;
1>
1'
16
0/
00
1:
15
01
02
03
04
1=
0+
0*
0)
#6
0$
0(
0"
0!
0-
09
0<
07
x.
0;
0>
1+
#7
1(
x&
x/
1<
1"
17
0.
1;
0#
1>
0'
06
0:
1!
0+
1*
#8
0(
0/
0<
07
x0
0;
1#
0>
1+
#9
x%
1$
x&
1(
x3
19
x"
17
1;
1#
1>
1'
16
00
1:
0!
05
0=
0+
0*
1)
#10
03
09
1%
07
x4
0;
0>
1+
#11
x&
0(
1$
x1
1"
17
04
1;
0#
1>
0'
06
0:
1!
0+
1*
#12
x$
1(
01
07
x2
0;
1#
0>
1+
#15
1&
1%
1$
19
1-
1<
0"
18
17
1;
1#
1>
1'
16
1:
1!
15
02
1=
0,
0+
0*
0)
#16
0%
0$
0&
1"
0-
08
1,
#17
1%
0(
0"
0!
09
0<
18
07
0;
0>
0,
1+
#18
0%
1&
08
1.
1,
#19
1(
0&
1<
1"
18
17
0.
1;
0#
1>
0'
06
0:
1!
0,
0+
1*
#20
1%
1&
08
1/
1,
#21
0%
0(
1&
10
0<
18
0/
07
0;
1#
0>
0,
1+
#22
0&
1%
00
08
1,
#23
1%
1$
1(
19
0"
18
17
1;
1#
1>
1'
16
1:
0!
05
0=
0,
0+
0*
1)
#24
0%
1&
1"
08
13
1,
#25
1&
0"
14
09
1%
18
03
07
0;
0>
0,
1+
#26
0&
04
1"
08
1,
#27
1&
1$
0(
11
18
17
1;
0#
1>
0'
06
0:
1!
0,
0+
1*
#28
0&
01
08
1,
#29
1(
18
07
0;
1#
0>
0,
1+
#30
1&
0$
08
12
1,
#35
1$
1%
1&
19
1-
1<
0"
18
17
1;
1#
1>
1'
16
1:
1!
15
02
1=
0,
0+
0*
0)
#36
0%
0$
0&
1"
0-
08
1,
#37
1%
0(
0"
0!
09
0<
18
07
0;
0>
0,
1+
#38
0%
1&
08
1.
1,
#39
1(
0&
1<
1"
18
17
0.
1;
0#
1>
0'
06
0:
1!
0,
0+
1*
#40
1%
1&
08
1/
1,
#41
0%
0(
1&
10
0<
18
0/
07
0;
1#
0>
0,
1+
#42
0&
1%
00
08
1,
#43
1%
1$
1(
19
0"
18
17
1;
1#
1>
1'
16
1:
0!
05
0=
0,
0+
0*
1)
#44
0%
1&
1"
08
13
1,
#45
1&
0"
14
09
1%
18
03
07
0;
0>
0,
1+
#46
0&
04
1"
08
1,
#47
1&
1$
0(
11
18
17
1;
0#
1>
0'
06
0:
1!
0,
0+
1*
#48
0&
01
08
1,
#49
1(
18
07
0;
1#
0>
0,
1+
#50
1&
0$
08
12
1,
#55
1$
1%
1&
19
1-
1<
0"
18
17
1;
1#
1>
1'
16
1:
1!
15
02
1=
0,
0+
0*
0)
#56
0%
0$
0&
1"
0-
08
1,
#57
1%
0(
0"
0!
09
0<
18
07
0;
0>
0,
1+
#58
0%
1&
08
1.
1,
#59
1(
0&
1<
1"
18
17
0.
1;
0#
1>
0'
06
0:
1!
0,
0+
1*
#60
1%
1&
08
1/
1,
#61
0%
0(
1&
10
0<
18
0/
07
0;
1#
0>
0,
1+
#62
0&
1%
00
08
1,
#63
1%
1$
1(
19
0"
18
17
1;
1#
1>
1'
16
1:
0!
05
0=
0,
0+
0*
1)
#64
0%
1&
1"
08
13
1,
#65
1&
0"
14
09
1%
18
03
07
0;
0>
0,
1+
#66
0&
04
1"
08
1,
#67
1&
1$
0(
11
18
17
1;
0#
1>
0'
06
0:
1!
0,
0+
1*
#68
0&
01
08
1,
#69
1(
18
07
0;
1#
0>
0,
1+
#70
1&
0$
08
12
1,
