ed1_lab8/ejercicio03/ejercicio3.v
///// ELECTRÓNICA DIGITAL 1
///// AXEL MAZARIEGOS - 131212
///// 23 - OCTUBRE - 2020
/////
///// LABORATORIO 08
///// EJERCICIO 03




module alu(input wire [11:0] a,
           input wire [11:0] b,
           input wire [2:0] fun,
           output reg [11:0] y);

  

  always@(posedge fun or posedge a or posedge b)     
    begin

      y = 0;

      case(fun)
        0: y = a & b;
        1: y = a | b;
        2: y = a + b;
        3: y = 0;
        4: y = a & ~b;
        5: y = a | ~b;
        6: y = a - b;
        7: if (a < b) y <= 12'b111111111111;
           else y <= 0;
      endcase 
    end
endmodule

ed1_lab10/ejercicio02/ejercicio2_tb.v
///// ELECTRÓNICA DIGITAL 1
///// AXEL MAZARIEGOS - 131212
///// 23 - OCTUBRE - 2020
/////
///// LABORATORIO 08
///// EJERCICIO 03

module ejercicio3();

  //variables 
  reg [2:0] F;
  reg [11:0] A;
  reg [11:0] B;
  wire [11:0] Y;


  alu U1(A, B, F, Y);
  

  initial begin
    #5 $display(" ");
    $display(" ");
    $display(" Contador ");
    $display("F A B | Y");
    $display("--------|---");
    $monitor("%b %b %b | %b ", F, A, B, Y);
  
    A = 12'b000110100010; //418 será el valor 
    B = 12'b001000000000; //512 será el valor 

    //reset (para iniciar en 0)
    #10 F = 0;
    #10 F = 1;
    #10 F = 2;
    #10 F = 3;
    #10 F = 4;
    #10 F = 5;
    #10 F = 6;
    #10 F = 7;
    #10  $finish;
  end


  initial begin
    $dumpfile("ejercicio3_tb.vcd");
    $dumpvars(0, ejercicio3);
  end

endmodule

ed1_lab8/ejercicio03/ejercicio3_tb.vcd
$date
	Sat Oct 24 23:22:24 2020
$end
$version
	Icarus Verilog
$end
$timescale
	1ps
$end
$scope module ejercicio3 $end
$var wire 12 ! Y [11:0] $end
$var reg 12 " A [11:0] $end
$var reg 12 # B [11:0] $end
$var reg 3 $ F [2:0] $end
$scope module U1 $end
$var wire 12 % a [11:0] $end
$var wire 12 & b [11:0] $end
$var wire 3 ' fun [2:0] $end
$var reg 12 ( y [11:0] $end
$upscope $end
$upscope $end
$enddefinitions $end
#0
$dumpvars
bx (
bx '
bx &
bx %
bx $
bx #
bx "
bx !
$end
#5
b1000000000 #
b1000000000 &
b110100010 "
b110100010 %
#15
b0 $
b0 '
#25
b1110100010 !
b1110100010 (
b1 $
b1 '
#35
b10 $
b10 '
#45
b0 !
b0 (
b11 $
b11 '
#55
b100 $
b100 '
#65
b110111111111 !
b110111111111 (
b101 $
b101 '
#75
b110 $
b110 '
#85
b111111111111 !
b111111111111 (
b111 $
b111 '
