04_tabla_POS/tabla04pos_tb.v
module tabla04pos();

// POS de la tabla 04

  reg A, B, C, D;
  wire o1, o2, o3, o4, o5, o6, o7, o8, o9, Y;

  // not (salida, entrada);
  // or (salida, entrada1, entrada2, entrada3, etc);
  // and (salida, entrada1, entrada2, entrada3, etc);

  or  U1(o1,  A,  B,  C, ~D);
  or  U2(o2,  A, ~B,  C,  D);
  or  U3(o3,  A, ~B,  C, ~D);
  or  U4(o4, ~A,  B,  C, ~D);
  or  U5(o5, ~A,  B, ~C, ~D);
  or  U6(o6, ~A, ~B,  C,  D);
  or  U7(o7, ~A, ~B,  C, ~D);
  or  U8(o8, ~A, ~B, ~C,  D);
  or  U9(o9, ~A, ~B, ~C, ~D);

  and U10(Y, o1, o2, o3, o4, o5, o6, o7, o8, o9);


  initial begin
    $display("A B C D | Y");
    $display("--------|--");
    $monitor("%b %b %b %b | %b", A, B, C, D, Y);
       A = 0; B = 0; C = 0; D = 0;
    #1                      D = 1;
    #1               C = 1; D = 0;
    #1                      D = 1;
    #1        B = 1; C = 0; D = 0;
    #1                      D = 1;
    #1               C = 1; D = 0;
    #1                      D = 1;
    #1 A = 1; B = 0; C = 0; D = 0;
    #1                      D = 1;
    #1               C = 1; D = 0;
    #1                      D = 1;
    #1        B = 1; C = 0; D = 0;
    #1                      D = 1;
    #1               C = 1; D = 0;
    #1                      D = 1;
    #1 $finish;
  end

  initial
    begin
      $dumpfile("tabla04pos_tb.vcd");
      $dumpvars(0, tabla04pos);
    end

endmodule

04_tabla_POS/tabla04pos_tb.vcd
$date
	Sat Aug  1 19:21:02 2020
$end
$version
	Icarus Verilog
$end
$timescale
	1ps
$end
$scope module tabla04pos $end
$var wire 1 ! Y $end
$var wire 1 " o1 $end
$var wire 1 # o2 $end
$var wire 1 $ o3 $end
$var wire 1 % o4 $end
$var wire 1 & o5 $end
$var wire 1 ' o6 $end
$var wire 1 ( o7 $end
$var wire 1 ) o8 $end
$var wire 1 * o9 $end
$var reg 1 + A $end
$var reg 1 , B $end
$var reg 1 - C $end
$var reg 1 . D $end
$upscope $end
$enddefinitions $end
#0
$dumpvars
0.
0-
0,
0+
1*
1)
1(
1'
1&
1%
1$
1#
1"
1!
$end
#1
0!
0"
1.
#2
1!
1"
0.
1-
#3
1.
#4
0!
1$
0#
0.
0-
1,
#5
0!
0$
1#
1.
#6
1!
1$
0.
1-
#7
1.
#8
1!
1&
1%
0.
0-
0,
1+
#9
0!
0%
1.
#10
1!
1%
0.
1-
#11
0!
0&
1.
#12
1(
0'
1&
0.
0-
1,
#13
0!
0(
1'
1.
#14
0)
1(
0.
1-
#15
0!
0*
1)
1.
