ed1_lab9/ejercicio04/ejercicio4.v
///// ELECTRÓNICA DIGITAL 1
///// AXEL MAZARIEGOS - 131212
///// 30 - OCTUBRE - 2020
/////
///// LABORATORIO 09
///// EJERCICIO 04


// Buffer Tri-estado
module triestado(input  [3:0] A,
                 input  EN,
                 output  [3:0] Y);

  assign Y = EN ? A : 4'bZZZZ;

endmodule

ed1_lab9/ejercicio04/ejercicio4_tb.v
///// ELECTRÓNICA DIGITAL 1
///// AXEL MAZARIEGOS - 131212
///// 30 - OCTUBRE - 2020
/////
///// LABORATORIO 09
///// EJERCICIO 04


module ejercicio4();

  //para las pruebas se usara el mismo clock, reset y enable para todos los FF
  
  reg [3:0] a;
  reg enable;
  wire [3:0] y;
  
  
  triestado U1(a, enable, y);

  initial begin
    #5 $display(" ");
    $display(" ");
    $display(" Buffer Tri-Estado ");
    $display("a    e |  y");
    $display("-------|-----");
    $monitor("%b %b | %b ", a, enable, y);
  end

  initial begin

    //prueba 1
    a = 4'b1010; 
    enable = 1;
    #10

    enable = 0; 
    #10

    enable = 1;
    #10

    enable = 0; 
    #10

    //prueba 2
    a = 4'b0110; 
    enable = 1;
    #10

    enable = 0; 
    #10

    enable = 1;
    #10

    enable = 0; 
    #10


    $finish;
  end


  initial begin
    $dumpfile("ejercicio4_tb.vcd");
    $dumpvars(0, ejercicio4);
  end

endmodule

ed1_lab9/ejercicio04/ejercicio4_tb.vcd
$date
	Sat Oct 31 09:33:19 2020
$end
$version
	Icarus Verilog
$end
$timescale
	1ps
$end
$scope module ejercicio4 $end
$var wire 4 ! y [3:0] $end
$var reg 4 " a [3:0] $end
$var reg 1 # enable $end
$scope module U1 $end
$var wire 4 $ A [3:0] $end
$var wire 1 # EN $end
$var wire 4 % Y [3:0] $end
$upscope $end
$upscope $end
$enddefinitions $end
#0
$dumpvars
b1010 %
b1010 $
1#
b1010 "
b1010 !
$end
#10
bz !
bz %
0#
#20
b1010 !
b1010 %
1#
#30
bz !
bz %
0#
#40
b110 !
b110 %
1#
b110 "
b110 $
#50
bz !
bz %
0#
#60
b110 !
b110 %
1#
#70
bz !
bz %
0#
