01_tabla_SOP/tabla01sop_tb.v
module tabla01sop();

// SOP de la tabla 01

  reg A, B, C;
  wire o1, o2, o3, o4, o5, Y;

  // not (salida, entrada);
  // or (salida, entrada1, entrada2, entrada3, etc);
  // and (salida, entrada1, entrada2, entrada3, etc);

  and  U1(o1, ~A, ~B, ~C);
  and  U2(o2, ~A,  B, ~C);
  and  U3(o3,  A, ~B, ~C);
  and  U4(o4,  A, ~B,  C);
  and  U5(o5,  A,  B,  C);

  or U6(Y, o1, o2, o3, o4, o5);


  initial begin
    $display("A B C | Y");
    $display("------|--");
    $monitor("%b %b %b | %b", A, B, C, Y);
    A = 0; B = 0; C = 0;
    #1               C = 1;
    #1        B = 1; C = 0;
    #1               C = 1;
    #1 A = 1; B = 0; C = 0;
    #1               C = 1;
    #1        B = 1; C = 0;
    #1               C = 1;
    #1 $finish;
  end

  initial
    begin
      $dumpfile("tabla01sop_tb.vcd");
      $dumpvars(0, tabla01sop);
    end

endmodule

ed1_lab3/01_tabla_SOP/tabla01sop_tb.vcd
$date
	Sat Aug  1 17:57:33 2020
$end
$version
	Icarus Verilog
$end
$timescale
	1ps
$end
$scope module tabla01sop $end
$var wire 1 ! Y $end
$var wire 1 " o1 $end
$var wire 1 # o2 $end
$var wire 1 $ o3 $end
$var wire 1 % o4 $end
$var wire 1 & o5 $end
$var reg 1 ' A $end
$var reg 1 ( B $end
$var reg 1 ) C $end
$upscope $end
$enddefinitions $end
#0
$dumpvars
0)
0(
0'
0&
0%
0$
0#
1"
1!
$end
#1
0!
0"
1)
#2
1!
1#
0)
1(
#3
0!
0#
1)
#4
1!
1$
0)
0(
1'
#5
0$
1%
1)
#6
0!
0%
0)
1(
#7
1!
1&
1)
